Metadata-Version: 2.1
Name: oneNeuron-pypi-LijiAlex
Version: 0.0.6
Summary: its a implementation of Perceptron
Home-page: https://github.com/LijiAlex/oneNeuron_pypi
Author: LijiAlex
Author-email: liji.alex@gmail.com
License: UNKNOWN
Project-URL: Bug Tracker, https://github.com/LijiAlex/oneNeuron_pypi/issues
Platform: UNKNOWN
Classifier: Programming Language :: Python :: 3
Classifier: License :: OSI Approved :: MIT License
Classifier: Operating System :: OS Independent
Requires-Python: >=3.7
License-File: LICENSE
Requires-Dist: numpy
Requires-Dist: tqdm
